LICENSE
MANIFEST.in
README.md
README.rst
requirements.txt
setup.py
Restcord.egg-info/PKG-INFO
Restcord.egg-info/SOURCES.txt
Restcord.egg-info/dependency_links.txt
Restcord.egg-info/requires.txt
Restcord.egg-info/top_level.txt
restcord/__init__.py
restcord/core.py
restcord/http.py
restcord/models.py
restcord/vars.py