Metadata-Version: 1.1
Name: Restcord
Version: 1.0.6
Summary: Restcord is a rest API wrapper for the Discord API, but this one does not include WebSockets, this is for people who dont want websockets but only make requests to the api.
Home-page: https://github.com/JustMaffie/Restcord
Author: JustMaffie
Author-email: UNKNOWN
License: MIT
Platform: UNKNOWN
Classifier: Development Status :: 4 - Beta
Classifier: License :: OSI Approved :: MIT License
Classifier: Intended Audience :: Developers
Classifier: Natural Language :: English
Classifier: Operating System :: OS Independent
Classifier: Programming Language :: Python :: 3.4
Classifier: Programming Language :: Python :: 3.5
Classifier: Topic :: Internet
Classifier: Topic :: Software Development :: Libraries
Classifier: Topic :: Software Development :: Libraries :: Python Modules
Classifier: Topic :: Utilities
